seokxkyu_cmd/__init__.py
seokxkyu_cmd/cmd.py
Seokxkyu_cmd-0.1.1.dist-info/METADATA
Seokxkyu_cmd-0.1.1.dist-info/WHEEL
Seokxkyu_cmd-0.1.1.dist-info/entry_points.txt
Seokxkyu_cmd-0.1.1.dist-info/top_level.txt
Seokxkyu_cmd-0.1.1.dist-info/RECORD
