Metadata-Version: 2.1
Name: Seokxkyu_cmd
Version: 0.1.1
Summary: Default template for PDM package
Author-email: Seokxkyu <kyuseok000@gmail.com>
License: MIT
Requires-Python: >=3.9
Requires-Dist: Seokxkyu-lotto >=0.2.0
